[{"date": "20230423", "month": "april", "day": "23", "type": "trail", "name": "KVANTUMLOPPET TRAIL", "distance": "7 km , 17 km", "distance_m": [17000], "place": "", "latitude": 0, "longitude": 0, "organizer": "", "website": "https://huddingeais.se/event/kvantumloppet-2023/", "src_url": "https://trailrunningsweden.se/trailkalendern/"}, {"date": "20230430", "month": "april", "day": "30", "type": "trail", "name": "GOTLAND REBEL RACE 2", "distance": "22 km, 11 km", "distance_m": [22000, 11000], "place": "", "latitude": 0, "longitude": 0, "organizer": "", "website": "https://raceid.com/sv/races/9813/information", "src_url": "https://trailrunningsweden.se/trailkalendern/"}, {"date": "20230513", "month": "maj", "day": "13", "type": "trail", "name": "Borgarloppet 2023", "distance": "knattar 0,6 km, flickor och pojkar 2,5 km, 6,0 km, 13 km, 23 km", "distance_m": [], "place": "", "latitude": 0, "longitude": 0, "organizer": "", "website": "https://forsaok.se/arrangemang/borgarloppet/", "src_url": "https://trailrunningsweden.se/trailkalendern/"}, {"date": "20230617", "month": "juni", "day": "17", "type": "trail", "name": "Ramsviks Trail 2023", "distance": "15 km, 8,5 km", "distance_m": [15000, 8000], "place": "", "latitude": 0, "longitude": 0, "organizer": "", "website": "https://ramsvikstrail.arenatime.se/", "src_url": "https://trailrunningsweden.se/trailkalendern/"}, {"date": "20230729", "month": "juli", "day": "29", "type": "trail", "name": "Hamra Trail Distans", "distance": "24 km", "distance_m": [24000], "place": "", "latitude": 0, "longitude": 0, "organizer": "", "website": "http://www.hamratrail.se", "src_url": "https://trailrunningsweden.se/trailkalendern/"}, {"date": "20230730", "month": "juli", "day": "30", "type": "trail", "name": "Hamra Trail Sprint", "distance": "9", "distance_m": [], "place": "", "latitude": 0, "longitude": 0, "organizer": "", "website": "http://www.hamratrail.se", "src_url": "https://trailrunningsweden.se/trailkalendern/"}, {"date": "20230910", "month": "september", "day": "10", "type": "trail", "name": "VMX - Vånga Mountain Xtreme", "distance": "8 km, 16 km, 40 km", "distance_m": [8000, 16000, 40000], "place": "", "latitude": 0, "longitude": 0, "organizer": "", "website": "https://www.vmxtreme.se/", "src_url": "https://trailrunningsweden.se/trailkalendern/"}, {"date": "20231007", "month": "oktober", "day": "07", "type": "trail", "name": "Rya Åsar Trail Run", "distance": "11,6 km", "distance_m": [11000], "place": "", "latitude": 0, "longitude": 0, "organizer": "", "website": "https://ryaasartrailrun.se", "src_url": "https://trailrunningsweden.se/trailkalendern/"}]