[
  {
    "date": "20230507",
    "month": "maj",
    "day": "07",
    "type": "trail",
    "name": "Borås Trail Run",
    "distance": "12 km, 22 km",
    "distance_m": [12000, 22000],
    "place": "",
    "latitude": 0,
    "longitude": 0,
    "organizer": "",
    "website": "https://www.borastrailrun.se/",
    "src_url": "https://trailrunningsweden.se/trailkalendern/"
  },
  {
    "date": "20230527",
    "month": "maj",
    "day": "27",
    "type": "trail",
    "name": "VirsboRUN",
    "distance": "0,8 km, 5,3 km, 10,6 km, 15,9 km, 21,2 km",
    "distance_m": [0, 5000, 10000, 15000, 21000],
    "place": "",
    "latitude": 0,
    "longitude": 0,
    "organizer": "",
    "website": "http://virsborun.se/",
    "src_url": "https://trailrunningsweden.se/trailkalendern/"
  },
  {
    "date": "20230701",
    "month": "juli",
    "day": "01",
    "type": "trail",
    "name": "Öppet Fjäll p/b Bergans",
    "distance": "25 km, 43 km",
    "distance_m": [25000, 43000],
    "place": "",
    "latitude": 0,
    "longitude": 0,
    "organizer": "",
    "website": "https://fjallmaraton.se/oppet-fjall/",
    "src_url": "https://trailrunningsweden.se/trailkalendern/"
  },
  {
    "date": "20230729",
    "month": "juli",
    "day": "29",
    "type": "trail",
    "name": "Kia Fjällmaraton Årefjällen",
    "distance": "0,6 km, 1,6 km, 5 km, 8 km, 12 km, 27 km, 45 km, 100 km",
    "distance_m": [0, 1000, 5000, 8000, 12000, 27000, 45000, 100000],
    "place": "",
    "latitude": 0,
    "longitude": 0,
    "organizer": "",
    "website": "https://fjallmaraton.se/fjallmaratonveckan/",
    "src_url": "https://trailrunningsweden.se/trailkalendern/"
  },
  {
    "date": "20230730",
    "month": "juli",
    "day": "30",
    "type": "trail",
    "name": "Salomon 27K",
    "distance": "27 km",
    "distance_m": [27000],
    "place": "",
    "latitude": 0,
    "longitude": 0,
    "organizer": "",
    "website": "https://fjallmaraton.se/fjallmaratonveckan/salomon-27k/",
    "src_url": "https://trailrunningsweden.se/trailkalendern/"
  },
  {
    "date": "20230729",
    "month": "juli",
    "day": "29",
    "type": "trail",
    "name": "Kia Fjällmaraton Årefjällen",
    "distance": "0,6 km, 1,6 km, 5 km, 8 km, 12 km, 27 km, 45 km, 100 km",
    "distance_m": [0, 1000, 5000, 8000, 12000, 27000, 45000, 100000],
    "place": "",
    "latitude": 0,
    "longitude": 0,
    "organizer": "",
    "website": "https://fjallmaraton.se/fjallmaratonveckan/",
    "src_url": "https://trailrunningsweden.se/trailkalendern/"
  },
  {
    "date": "20230801",
    "month": "augusti",
    "day": "01",
    "type": "trail",
    "name": "Peak Performance Vertical K",
    "distance": "5 km",
    "distance_m": [5000],
    "place": "",
    "latitude": 0,
    "longitude": 0,
    "organizer": "",
    "website": "https://fjallmaraton.se/fjallmaratonveckan/vertical-k/",
    "src_url": "https://trailrunningsweden.se/trailkalendern/"
  },
  {
    "date": "20230803",
    "month": "augusti",
    "day": "03",
    "type": "trail",
    "name": "Fjällmaraton 100 K p/b Buff",
    "distance": "100 km",
    "distance_m": [100000],
    "place": "",
    "latitude": 0,
    "longitude": 0,
    "organizer": "",
    "website": "https://fjallmaraton.se/fjallmaratonveckan/fjallmaraton-100k/",
    "src_url": "https://trailrunningsweden.se/trailkalendern/"
  },
  {
    "date": "20230805",
    "month": "augusti",
    "day": "05",
    "type": "trail",
    "name": "Kia Fjällmaraton 45 K",
    "distance": "45 K",
    "distance_m": [],
    "place": "",
    "latitude": 0,
    "longitude": 0,
    "organizer": "",
    "website": "https://fjallmaraton.se/fjallmaratonveckan/fjallmaraton/",
    "src_url": "https://trailrunningsweden.se/trailkalendern/"
  },
  {
    "date": "20230820",
    "month": "augusti",
    "day": "20",
    "type": "trail",
    "name": "Trollhättan City Trail",
    "distance": "10 km",
    "distance_m": [10000],
    "place": "",
    "latitude": 0,
    "longitude": 0,
    "organizer": "",
    "website": "https://www.alliansloppet.se/trollhattan-city-trail/",
    "src_url": "https://trailrunningsweden.se/trailkalendern/"
  },
  {
    "date": "20230902",
    "month": "september",
    "day": "02",
    "type": "trail",
    "name": "Fjällmaraton Sälen by EQPE",
    "distance": "42 km, 21 km, 10 km",
    "distance_m": [42000, 21000, 10000],
    "place": "",
    "latitude": 0,
    "longitude": 0,
    "organizer": "",
    "website": "https://www.fjallmaratonsalen.se/",
    "src_url": "https://trailrunningsweden.se/trailkalendern/"
  },
  {
    "date": "20230916",
    "month": "september",
    "day": "16",
    "type": "trail",
    "name": "H2 Ultra Trail",
    "distance": "28 km, 50 km, 100 km",
    "distance_m": [28000, 50000, 100000],
    "place": "",
    "latitude": 0,
    "longitude": 0,
    "organizer": "",
    "website": "https://www.okskogsvargarna.se",
    "src_url": "https://trailrunningsweden.se/trailkalendern/"
  },
  {
    "date": "20230916",
    "month": "september",
    "day": "16",
    "type": "trail",
    "name": "Lasse-Majaloppet",
    "distance": "1,5 km, 6 km, 13 km, 23 km",
    "distance_m": [1000, 6000, 13000, 23000],
    "place": "",
    "latitude": 0,
    "longitude": 0,
    "organizer": "",
    "website": "https://www.svenskalag.se/arbogask-lassemaja",
    "src_url": "https://trailrunningsweden.se/trailkalendern/"
  }
]
